shape_merge/__init__.py
shape_merge/merge.py
shape_merge/save.py
shape_merge-1.0.3.dist-info/LICENSE.txt
shape_merge-1.0.3.dist-info/METADATA
shape_merge-1.0.3.dist-info/WHEEL
shape_merge-1.0.3.dist-info/top_level.txt
shape_merge-1.0.3.dist-info/RECORD
