Metadata-Version: 2.1
Name: shape-merge
Version: 1.0.3
Summary: Library that Merges Geo Spatial Shapes
Home-page: https://github.com/fuzailpalnak/ShapeMerge
Author: Fuzail Palnak
Author-email: fuzailpalnak@gmail.com
Keywords: GIS, Merge, Shapely, Fiona, Polygon, MultiPolygon, Geometry
Classifier: Programming Language :: Python :: 3
Classifier: License :: OSI Approved :: MIT License
Classifier: Topic :: Software Development :: Libraries
Classifier: Topic :: Software Development :: Libraries :: Python Modules
Classifier: Intended Audience :: Developers
Classifier: Operating System :: OS Independent
Requires-Python: ~=3.3
License-File: LICENSE.txt
Requires-Dist: shapely (==1.7.0)
Requires-Dist: geojson (>=2.5.0)
Requires-Dist: py-oneliner (==0.0.1)
